Workbook

Sheet Sheet1
A1: ITEM NAME | B1: QUANTITY | C1: PRICE PER UNIT | D1: TOTAL COST
A2: Redmi note 10 | B2: 3 | C2: 30099 | D2: 90297
A3: Google Pixel 8 pro | B3: 2 | C3: 132000 | D3: 264000
A4: iphone 14 | B4: 2 | C4: 183999 | D4: 367998
A5: samsung s24 ultra | B5: 1 | C5: 329999 | D5: 329999

Sheet Sheet2
A1: MONTHLY SALES REPORT - Q1 2024
A2: MONTH | B2: SALES | C2: PERFORMANCE
A3: March | B3: 45 | C3: Bad
A4: January | B4: 50 | C4: Bad
A5: February | B5: 180 | C5: Good

Sheet Sheet3
A1: PRODUCTS | B1: SALES
A2: Projector | B2: 50
A3: Laptop | B3: 65
A4: Air buds | B4: 40
A5: Head Phones | B5: 200

Sheet Sheet4
A1: S.NO | B1: NAME | C1: MARKS OUT OF 100 | D1: GRADE
A2: 1 | B2: Student 1 | C2: =RANDBETWEEN(0,100) -> 60 | D2: =IF(C2>=80,"A",IF(C2>=70,"B",IF(C2>=60,"C","D"))) -> C
A3: 2 | B3: Student 2 | C3: =RANDBETWEEN(0,100) -> 52 | D3: =IF(C3>=80,"A",IF(C3>=70,"B",IF(C3>=60,"C","D"))) -> D
A4: 3 | B4: Student 3 | C4: =RANDBETWEEN(0,100) -> 78 | D4: =IF(C4>=80,"A",IF(C4>=70,"B",IF(C4>=60,"C","D"))) -> B
A5: 4 | B5: Student 4 | C5: =RANDBETWEEN(0,100) -> 39 | D5: =IF(C5>=80,"A",IF(C5>=70,"B",IF(C5>=60,"C","D"))) -> D
A6: 5 | B6: Student 5 | C6: =RANDBETWEEN(0,100) -> 39 | D6: =IF(C6>=80,"A",IF(C6>=70,"B",IF(C6>=60,"C","D"))) -> D
A7: 6 | B7: Student 6 | C7: =RANDBETWEEN(0,100) -> 73 | D7: =IF(C7>=80,"A",IF(C7>=70,"B",IF(C7>=60,"C","D"))) -> B
A8: 7 | B8: Student 7 | C8: =RANDBETWEEN(0,100) -> 97 | D8: =IF(C8>=80,"A",IF(C8>=70,"B",IF(C8>=60,"C","D"))) -> A
A9: 8 | B9: Student 8 | C9: =RANDBETWEEN(0,100) -> 93 | D9: =IF(C9>=80,"A",IF(C9>=70,"B",IF(C9>=60,"C","D"))) -> A
A10: 9 | B10: Student 9 | C10: =RANDBETWEEN(0,100) -> 61 | D10: =IF(C10>=80,"A",IF(C10>=70,"B",IF(C10>=60,"C","D"))) -> C
A11: 10 | B11: Student 10 | C11: =RANDBETWEEN(0,100) -> 58 | D11: =IF(C11>=80,"A",IF(C11>=70,"B",IF(C11>=60,"C","D"))) -> D
A12: 11 | B12: Student 11 | C12: =RANDBETWEEN(0,100) -> 53 | D12: =IF(C12>=80,"A",IF(C12>=70,"B",IF(C12>=60,"C","D"))) -> D
A13: 12 | B13: Student 12 | C13: =RANDBETWEEN(0,100) -> 43 | D13: =IF(C13>=80,"A",IF(C13>=70,"B",IF(C13>=60,"C","D"))) -> D
... A101: 100 | B101: Student 100 | C101: =RANDBETWEEN(0,100) -> 25 | D101: =IF(C101>=80,"A",IF(C101>=70,"B",IF(C101>=60,"C","D"))) -> D

Sheet Sheet5
A1: S.NO | B1: VALUE | C1: 15% OF VALUE | D1: 0.15
A2: 1 | B2: 100 | C2: =B2*$D$1 -> 15
A3: 2 | B3: 200 | C3: =B3*$D$1 -> 30
A4: 3 | B4: 300 | C4: =B4*$D$1 -> 45
A5: 4 | B5: 400 | C5: =B5*$D$1 -> 60
A6: 5 | B6: 500 | C6: =B6*$D$1 -> 75

Sheet Sheet6

Sheet Sheet7
A1: Sir Qasim Subject : Request for GCR class code Respected Sir , I hope you are doing well. I am student of CE 1 semester .I am writing to kindly request the GCR (Google Classroom) class code for our course. I need the code to join the class and access the course materials, assignments, and announcements. Hania Usman 26P-6542 CE A1
J2: ROLL NO | K2: STUDENT NAME | L2: DEPARTMENT | M2: MARKS | N2: GRADE | P2: FEATURES APPLIED :
J3: 1005 | K3: Aiman | L3: CE | M3: 43 | N3: F | P3: DATA VALIDATION : Created a drop down list to allow only
J4: 1002 | K4: Aleezay | L4: IT | M4: 45 | N4: F | P4: predefined values in the starting colum
J5: 1003 | K5: Dua | L5: AI | M5: 68 | N5: B | P5: REMOVE DUPLICATE : use to identify and remove duplicates
J6: 1001 | K6: Anoosha | L6: CS | M6: 82 | N6: A | P6: CONDITIONAL FORMATTING :Highlites cell based on specific condition .
J7: 1004 | K7: Tadin | L7: CE | M7: 88 | N7: A+
A23: TASK 7: 26P-6542

Sheet Sheet8
G1: PRICE | H1: LOCATION | I1: CITY | J1: PROVINCE NAME | K1: PURPOSE | L1: STARS | N1: ISLAMABAD CAPITAL | O1: PUNJAB | P1: SINDH
A2: 128983 | B2: 478 | C2: House | D2: 8 | E2: 8 | F2: 43483 | G2: =VLOOKUP(A2,Sheet9!$A:$F,2,FALSE) -> 200000 | H2: =VLOOKUP(A2,Sheet9!$A:$F,3,FALSE ) -> Adiala Road | I2: =VLOOKUP(A2,Sheet9!$A:$F,4,FALSE) -> Rawalpindi | J2: =VLOOKUP(A2,Sheet9!$A:$F,5,FALSE) -> Punjab | K2: =VLOOKUP(A2,Sheet9!$A:$F,6,FALSE) -> For Rent | L2: =HLOOKUP(J2,$N$1:$P$2,2,FALSE) -> 2 | N2: 3 | O2: 2 | P2: 1
A3: 237062 | B3: 3325 | C3: Flat | D3: 2 | E3: 2 | F3: 43500 | G3: =VLOOKUP(A3,Sheet9!$A:$F,2,FALSE) -> 10000000 | H3: =VLOOKUP(A3,Sheet9!$A:$F,3,FALSE ) -> G-10 | I3: =VLOOKUP(A3,Sheet9!$A:$F,4,FALSE) -> Islamabad | J3: =VLOOKUP(A3,Sheet9!$A:$F,5,FALSE) -> Islamabad Capital | K3: =VLOOKUP(A3,Sheet9!$A:$F,6,FALSE) -> For Sale | L3: =HLOOKUP(J3,$N$1:$P$2,2,FALSE) -> 3
A4: 342005 | B4: 232 | C4: House | D4: 8 | E4: 6 | F4: 43664 | G4: =VLOOKUP(A4,Sheet9!$A:$F,2,FALSE) -> 35000000 | H4: =VLOOKUP(A4,Sheet9!$A:$F,3,FALSE ) -> Gulistan-e-Jauhar | I4: =VLOOKUP(A4,Sheet9!$A:$F,4,FALSE) -> Karachi | J4: =VLOOKUP(A4,Sheet9!$A:$F,5,FALSE) -> Sindh | K4: =VLOOKUP(A4,Sheet9!$A:$F,6,FALSE) -> For Sale | L4: =HLOOKUP(J4,$N$1:$P$2,2,FALSE) -> 1
A5: 346905 | B5: 3236 | C5: Flat | D5: 3 | E5: 3 | F5: 43589 | G5: =VLOOKUP(A5,Sheet9!$A:$F,2,FALSE) -> 6900000 | H5: =VLOOKUP(A5,Sheet9!$A:$F,3,FALSE ) -> E-11 | I5: =VLOOKUP(A5,Sheet9!$A:$F,4,FALSE) -> Islamabad | J5: =VLOOKUP(A5,Sheet9!$A:$F,5,FALSE) -> Islamabad Capital | K5: =VLOOKUP(A5,Sheet9!$A:$F,6,FALSE) -> For Sale | L5: =HLOOKUP(J5,$N$1:$P$2,2,FALSE) -> 3
A6: 347795 | B6: 8 | C6: House | D6: 0 | E6: 0 | F6: 43663 | G6: =VLOOKUP(A6,Sheet9!$A:$F,2,FALSE) -> 220000000 | H6: =VLOOKUP(A6,Sheet9!$A:$F,3,FALSE ) -> Model Town | I6: =VLOOKUP(A6,Sheet9!$A:$F,4,FALSE) -> Lahore | J6: =VLOOKUP(A6,Sheet9!$A:$F,5,FALSE) -> Punjab | K6: =VLOOKUP(A6,Sheet9!$A:$F,6,FALSE) -> For Sale | L6: =HLOOKUP(J6,$N$1:$P$2,2,FALSE) -> 2
A7: 386513 | B7: 764 | C7: House | D7: 6 | E7: 5 | F7: 43663 | G7: =VLOOKUP(A7,Sheet9!$A:$F,2,FALSE) -> 16500000 | H7: =VLOOKUP(A7,Sheet9!$A:$F,3,FALSE ) -> G-15 | I7: =VLOOKUP(A7,Sheet9!$A:$F,4,FALSE) -> Islamabad | J7: =VLOOKUP(A7,Sheet9!$A:$F,5,FALSE) -> Islamabad Capital | K7: =VLOOKUP(A7,Sheet9!$A:$F,6,FALSE) -> For Sale | L7: =HLOOKUP(J7,$N$1:$P$2,2,FALSE) -> 3
A8: 425947 | B8: 1406 | C8: House | D8: 4 | E8: 5 | F8: 43560 | G8: =VLOOKUP(A8,Sheet9!$A:$F,2,FALSE) -> 13500000 | H8: =VLOOKUP(A8,Sheet9!$A:$F,3,FALSE ) -> Humak | I8: =VLOOKUP(A8,Sheet9!$A:$F,4,FALSE) -> Rawalpindi | J8: =VLOOKUP(A8,Sheet9!$A:$F,5,FALSE) -> Punjab | K8: =VLOOKUP(A8,Sheet9!$A:$F,6,FALSE) -> For Sale | L8: =HLOOKUP(J8,$N$1:$P$2,2,FALSE) -> 2
A9: 466607 | B9: 1484 | C9: Flat | D9: 3 | E9: 3 | F9: 43393 | G9: =VLOOKUP(A9,Sheet9!$A:$F,2,FALSE) -> 21000000 | H9: =VLOOKUP(A9,Sheet9!$A:$F,3,FALSE ) -> DHA Defence | I9: =VLOOKUP(A9,Sheet9!$A:$F,4,FALSE) -> Karachi | J9: =VLOOKUP(A9,Sheet9!$A:$F,5,FALSE) -> Sindh | K9: =VLOOKUP(A9,Sheet9!$A:$F,6,FALSE) -> For Sale | L9: =HLOOKUP(J9,$N$1:$P$2,2,FALSE) -> 1
A10: 482892 | B10: 48 | C10: House | D10: 5 | E10: 5 | F10: 43379 | G10: =VLOOKUP(A10,Sheet9!$A:$F,2,FALSE) -> 40000000 | H10: =VLOOKUP(A10,Sheet9!$A:$F,3,FALSE ) -> Multan Road | I10: =VLOOKUP(A10,Sheet9!$A:$F,4,FALSE) -> Lahore | J10: =VLOOKUP(A10,Sheet9!$A:$F,5,FALSE) -> Punjab | K10: =VLOOKUP(A10,Sheet9!$A:$F,6,FALSE) -> For Sale | L10: =HLOOKUP(J10,$N$1:$P$2,2,FALSE) -> 2
A11: 487921 | B11: 6053 | C11: House | D11: 10 | E11: 12 | F11: 43650 | G11: =VLOOKUP(A11,Sheet9!$A:$F,2,FALSE) -> 31500000 | H11: =VLOOKUP(A11,Sheet9!$A:$F,3,FALSE ) -> Westridge | I11: =VLOOKUP(A11,Sheet9!$A:$F,4,FALSE) -> Rawalpindi | J11: =VLOOKUP(A11,Sheet9!$A:$F,5,FALSE) -> Punjab | K11: =VLOOKUP(A11,Sheet9!$A:$F,6,FALSE) -> For Sale | L11: =HLOOKUP(J11,$N$1:$P$2,2,FALSE) -> 2
A12: 488267 | B12: 3046 | C12: House | D12: 6 | E12: 6 | F12: 43663 | G12: =VLOOKUP(A12,Sheet9!$A:$F,2,FALSE) -> 23000000 | H12: =VLOOKUP(A12,Sheet9!$A:$F,3,FALSE ) -> Bahria Town Rawalpindi | I12: =VLOOKUP(A12,Sheet9!$A:$F,4,FALSE) -> Rawalpindi | J12: =VLOOKUP(A12,Sheet9!$A:$F,5,FALSE) -> Punjab | K12: =VLOOKUP(A12,Sheet9!$A:$F,6,FALSE) -> For Sale | L12: =HLOOKUP(J12,$N$1:$P$2,2,FALSE) -> 2
A13: 523420 | B13: 1484 | C13: House | D13: 0 | E13: 6 | F13: 43664 | G13: =VLOOKUP(A13,Sheet9!$A:$F,2,FALSE) -> 200000 | H13: =VLOOKUP(A13,Sheet9!$A:$F,3,FALSE ) -> DHA Defence | I13: =VLOOKUP(A13,Sheet9!$A:$F,4,FALSE) -> Karachi | J13: =VLOOKUP(A13,Sheet9!$A:$F,5,FALSE) -> Sindh | K13: =VLOOKUP(A13,Sheet9!$A:$F,6,FALSE) -> For Rent | L13: =HLOOKUP(J13,$N$1:$P$2,2,FALSE) -> 1
A14: 530579 | B14: 1673 | C14: House | D14: 0 | E14: 6 | F14: 43664 | G14: =VLOOKUP(A14,Sheet9!$A:$F,2,FALSE) -> 230000 | H14: =VLOOKUP(A14,Sheet9!$A:$F,3,FALSE ) -> DHA Defence | I14: =VLOOKUP(A14,Sheet9!$A:$F,4,FALSE) -> Karachi | J14: =VLOOKUP(A14,Sheet9!$A:$F,5,FALSE) -> Sindh | K14: =VLOOKUP(A14,Sheet9!$A:$F,6,FALSE) -> For Rent | L14: =HLOOKUP(J14,$N$1:$P$2,2,FALSE) -> 1
... A729: 6772376 | B729: 339 | C729: House | D729: 0 | E729: 4 | F729: 43628 | G729: =VLOOKUP(A729,Sheet9!$A:$F,2,FALSE) -> 26000000 | H729: =VLOOKUP(A729,Sheet9!$A:$F,3,FALSE ) -> DHA Defence | I729: =VLOOKUP(A729,Sheet9!$A:$F,4,FALSE) -> Islamabad | J729: =VLOOKUP(A729,Sheet9!$A:$F,5,FALSE) -> Islamabad Capital | K729: =VLOOKUP(A729,Sheet9!$A:$F,6,FALSE) -> For Sale | L729: =HLOOKUP(J729,$N$1:$P$2,2,FALSE) -> 3

Sheet Sheet9
A1: 86575 | B1: 450000000 | C1: Cantt | D1: Karachi | E1: Sindh | F1: For Sale
A2: 128983 | B2: 200000 | C2: Adiala Road | D2: Rawalpindi | E2: Punjab | F2: For Rent
A3: 237062 | B3: 10000000 | C3: G-10 | D3: Islamabad | E3: Islamabad Capital | F3: For Sale
A4: 342005 | B4: 35000000 | C4: Gulistan-e-Jauhar | D4: Karachi | E4: Sindh | F4: For Sale
A5: 346905 | B5: 6900000 | C5: E-11 | D5: Islamabad | E5: Islamabad Capital | F5: For Sale
A6: 347795 | B6: 220000000 | C6: Model Town | D6: Lahore | E6: Punjab | F6: For Sale
A7: 386513 | B7: 16500000 | C7: G-15 | D7: Islamabad | E7: Islamabad Capital | F7: For Sale
A8: 425947 | B8: 13500000 | C8: Humak | D8: Rawalpindi | E8: Punjab | F8: For Sale
A9: 466607 | B9: 21000000 | C9: DHA Defence | D9: Karachi | E9: Sindh | F9: For Sale
A10: 482892 | B10: 40000000 | C10: Multan Road | D10: Lahore | E10: Punjab | F10: For Sale
A11: 487921 | B11: 31500000 | C11: Westridge | D11: Rawalpindi | E11: Punjab | F11: For Sale
A12: 488267 | B12: 23000000 | C12: Bahria Town Rawalpindi | D12: Rawalpindi | E12: Punjab | F12: For Sale
... A2161: 8305205 | B2161: 130000 | C2161: E-11 | D2161: Islamabad | E2161: Islamabad Capital | F2161: For Rent
